[
    {
        "title": "【渗透测试】手把手带你玩转SSRF漏洞",
        "url": "https://mp.weixin.qq.com/s?__biz=Mzk0Mzc1MTI2Nw==&mid=2247494621&idx=1&sn=a7b114611aa3ad7a0527f47e53521481",
        "source": "Doonsec",
        "date_added": "2025-08-09"
    },
    {
        "title": "一次实战中命令执行回显绕过",
        "url": "https://mp.weixin.qq.com/s?__biz=MzkwODc1NTgyMg==&mid=2247487607&idx=1&sn=13f4fae09cb2790931fc318a912a322c",
        "source": "Doonsec",
        "date_added": "2025-08-09"
    },
    {
        "title": "漏洞预警 | 万户ezOFFICE SQL注入漏洞",
        "url": "https://mp.weixin.qq.com/s?__biz=MzkwMTQ0NDA1NQ==&mid=2247494014&idx=1&sn=c89b80c3f089b2e0bae5b72757cab215",
        "source": "Doonsec",
        "date_added": "2025-08-09"
    },
    {
        "title": "漏洞预警 | 金和OA XXE漏洞",
        "url": "https://mp.weixin.qq.com/s?__biz=MzkwMTQ0NDA1NQ==&mid=2247494014&idx=2&sn=d7e745190dfd0f5a13364c2154311b0a",
        "source": "Doonsec",
        "date_added": "2025-08-09"
    },
    {
        "title": "漏洞预警 | 汉王e脸通智慧园区管理平台SQL注入漏洞",
        "url": "https://mp.weixin.qq.com/s?__biz=MzkwMTQ0NDA1NQ==&mid=2247494014&idx=3&sn=f4709ee1ef3886bae1a03a25797196f5",
        "source": "Doonsec",
        "date_added": "2025-08-09"
    }
]