[
    {
        "title": "] [CISSP白皮书丨成功的网络安全领导者有什么共同的特质？",
        "url": "https://mp.weixin.qq.com/s?__biz=MzUzNTg4NDAyMg==&mid=2247493079&idx=1&sn=683ecefe1544d3e85a3db1055dec47ca",
        "source": "ChainReactors",
        "date_added": "2025-08-27"
    },
    {
        "title": "] [雷神众测漏洞周报2025.8.18-2025.8.24",
        "url": "https://mp.weixin.qq.com/s?__biz=MzI0NzEwOTM0MA==&mid=2652503509&idx=1&sn=9a1e062039b116955669eb29e45b656a",
        "source": "ChainReactors",
        "date_added": "2025-08-27"
    },
    {
        "title": "] [网络安全脱钩！微软停止向中国网络安全公司发送漏洞预警情报",
        "url": "https://mp.weixin.qq.com/s?__biz=MzA5ODA0NDE2MA==&mid=2649788976&idx=1&sn=b2160a1d5716028aa5743d0801f18ee7",
        "source": "ChainReactors",
        "date_added": "2025-08-27"
    },
    {
        "title": "] [Tableau 服务器中严重漏洞可导致攻击者上传恶意文件",
        "url": "https://mp.weixin.qq.com/s?__biz=MzI2NTg4OTc5Nw==&mid=2247523889&idx=1&sn=baef786161ffa4ee81a4cb94db27cd5f",
        "source": "ChainReactors",
        "date_added": "2025-08-27"
    },
    {
        "title": "] [漏洞通告 | 微步情报局再次发现DataEase存在高危漏洞",
        "url": "https://mp.weixin.qq.com/s?__biz=Mzg5MTc3ODY4Mw==&mid=2247507902&idx=1&sn=ef196d59c34733bf600830dc71d16500",
        "source": "ChainReactors",
        "date_added": "2025-08-27"
    },
    {
        "title": "] [【安全圈】Docker Desktop曝高危漏洞：恶意容器可劫持Windows主机",
        "url": "https://mp.weixin.qq.com/s?__biz=MzIzMzE4NDU1OQ==&mid=2652071388&idx=2&sn=73678592bffb2707d1938193f9c6ec31",
        "source": "ChainReactors",
        "date_added": "2025-08-27"
    },
    {
        "title": "] [Docker 修复 9.3 分高危漏洞，Win/mac 用户速升级",
        "url": "https://mp.weixin.qq.com/s?__biz=MjM5NTc2MDYxMw==&mid=2458598989&idx=3&sn=12ad73fc5a75757f5a26f9b787074cac",
        "source": "ChainReactors",
        "date_added": "2025-08-27"
    },
    {
        "title": "] [CNVD漏洞周报2025年第32期",
        "url": "https://mp.weixin.qq.com/s?__biz=MzIwNDk0MDgxMw==&mid=2247500294&idx=1&sn=f541162fb71587ca9fbeef21ada6bc5b",
        "source": "ChainReactors",
        "date_added": "2025-08-27"
    },
    {
        "title": "] [CISSP白皮书丨成功的网络安全领导者有什么共同的特质？",
        "url": "https://mp.weixin.qq.com/s?__biz=MzUzNTg4NDAyMg==&mid=2247493079&idx=1&sn=683ecefe1544d3e85a3db1055dec47ca",
        "source": "BruceFeIix",
        "date_added": "2025-08-27"
    },
    {
        "title": "] [网络安全脱钩！微软停止向中国网络安全公司发送漏洞预警情报",
        "url": "https://mp.weixin.qq.com/s?__biz=MzA5ODA0NDE2MA==&mid=2649788976&idx=1&sn=b2160a1d5716028aa5743d0801f18ee7",
        "source": "BruceFeIix",
        "date_added": "2025-08-27"
    },
    {
        "title": "] [雷神众测漏洞周报2025.8.18-2025.8.24",
        "url": "https://mp.weixin.qq.com/s?__biz=MzI0NzEwOTM0MA==&mid=2652503509&idx=1&sn=9a1e062039b116955669eb29e45b656a",
        "source": "BruceFeIix",
        "date_added": "2025-08-27"
    },
    {
        "title": "] [Tableau 服务器中严重漏洞可导致攻击者上传恶意文件",
        "url": "https://mp.weixin.qq.com/s?__biz=MzI2NTg4OTc5Nw==&mid=2247523889&idx=1&sn=baef786161ffa4ee81a4cb94db27cd5f",
        "source": "BruceFeIix",
        "date_added": "2025-08-27"
    },
    {
        "title": "] [漏洞通告 | 微步情报局再次发现DataEase存在高危漏洞",
        "url": "https://mp.weixin.qq.com/s?__biz=Mzg5MTc3ODY4Mw==&mid=2247507902&idx=1&sn=ef196d59c34733bf600830dc71d16500",
        "source": "BruceFeIix",
        "date_added": "2025-08-27"
    },
    {
        "title": "] [Docker 修复 9.3 分高危漏洞，Win/mac 用户速升级",
        "url": "https://mp.weixin.qq.com/s?__biz=MjM5NTc2MDYxMw==&mid=2458598989&idx=3&sn=12ad73fc5a75757f5a26f9b787074cac",
        "source": "BruceFeIix",
        "date_added": "2025-08-27"
    },
    {
        "title": "] [【安全圈】Docker Desktop曝高危漏洞：恶意容器可劫持Windows主机",
        "url": "https://mp.weixin.qq.com/s?__biz=MzIzMzE4NDU1OQ==&mid=2652071388&idx=2&sn=73678592bffb2707d1938193f9c6ec31",
        "source": "BruceFeIix",
        "date_added": "2025-08-27"
    },
    {
        "title": "] [CNVD漏洞周报2025年第32期",
        "url": "https://mp.weixin.qq.com/s?__biz=MzIwNDk0MDgxMw==&mid=2247500294&idx=1&sn=f541162fb71587ca9fbeef21ada6bc5b",
        "source": "BruceFeIix",
        "date_added": "2025-08-27"
    },
    {
        "title": "【严重】Dataease DB2 Aspectweaver 反序列化任意文件写入漏洞",
        "url": "https://mp.weixin.qq.com/s?__biz=Mzg4MDg5NzAxMQ==&mid=2247486028&idx=1&sn=5de99b5c36af6f971c1c756922f4c65f",
        "source": "Doonsec",
        "date_added": "2025-08-27"
    },
    {
        "title": "案例-记一次Flash网站渗透测试",
        "url": "https://mp.weixin.qq.com/s?__biz=MzI5NzA2MjgwNg==&mid=2648115761&idx=1&sn=9fc5081aebbc91a85f30ab02d59ab1b1",
        "source": "Doonsec",
        "date_added": "2025-08-27"
    },
    {
        "title": "十年渗透：俄罗斯APT组织如何长期利用思科设备漏洞",
        "url": "https://mp.weixin.qq.com/s?__biz=Mzg2MDg0ODg1NQ==&mid=2247548059&idx=2&sn=ace120ce9d6525cfae14fd01243f5eb0",
        "source": "Doonsec",
        "date_added": "2025-08-27"
    },
    {
        "title": ".NET MVC 漏洞挖掘，通过匿名访问实现权限绕过",
        "url": "https://mp.weixin.qq.com/s?__biz=MzUyOTc3NTQ5MA==&mid=2247500396&idx=3&sn=6aa7fa0dfd430326fedd9b3f6d4c19f4",
        "source": "Doonsec",
        "date_added": "2025-08-27"
    },
    {
        "title": "接代码审计项目",
        "url": "https://mp.weixin.qq.com/s?__biz=Mzg5ODgxMTIzMg==&mid=2247483919&idx=1&sn=d6070ee4bd99cb90dc18f2d5f92de798",
        "source": "Doonsec",
        "date_added": "2025-08-27"
    },
    {
        "title": "ssrf漏洞结合redis渗透linux主机",
        "url": "https://mp.weixin.qq.com/s?__biz=MzAwMjc0NTEzMw==&mid=2653589096&idx=1&sn=6c9c4ce08ec837ca9499d02f790d29d6",
        "source": "Doonsec",
        "date_added": "2025-08-27"
    },
    {
        "title": "php 文件上传不含一句 php 代码 RCE 最新新姿势",
        "url": "https://mp.weixin.qq.com/s?__biz=MzkxNzY5MTg1Ng==&mid=2247491382&idx=1&sn=b123c2aba693f923bf235b603ef684c4",
        "source": "Doonsec",
        "date_added": "2025-08-27"
    }
]